dreamcreator/__init__.py
dreamcreator/sequencecreator.py
dreamcreator/sequencecreatorvariables.py
dreamcreator/sequencetracker.py
dreamcreator/yamlcheck.py
dreamcreator/sequences/__init__.py
dreamcreator/sequences/BIO/__init__.py
dreamcreator/sequences/DREAM/__init__.py
dreamcreator/sequences/DREAM/current_sweep.py
dreamcreator/sequences/DREAM/set_current_wavelength_sweep.py
dreamcreator/sequences/DREAM/set_voltage_wavelength_sweep.py
dreamcreator/sequences/DREAM/set_wavelength_current_sweep.py
dreamcreator/sequences/DREAM/set_wavelength_voltage_sweep.py
dreamcreator/sequences/DREAM/voltage_sweep.py
dreamcreator/sequences/DREAM/wavelength_sweep.py
dreamcreator/sequences/IDA/__init__.py
dreamcreator/sequences/IDA/current_sweep_ida.py
dreamcreator/sequences/IDA/set_current_wavelength_sweep_ida.py
dreamcreator/sequences/IDA/set_voltage_wavelength_sweep_ida.py
dreamcreator/sequences/IDA/set_wavelength_current_sweep_ida.py
dreamcreator/sequences/IDA/set_wavelength_voltage_sweep_ida.py
dreamcreator/sequences/IDA/voltage_sweep_ida.py
dreamcreator/sequences/IDA/wavelength_sweep_ida.py
dreamcreator/sequences/core/__init__.py
dreamcreator/sequences/core/laser_sweep.py
dreamcreator/sequences/core/results.py
dreamcreator/sequences/core/sequence.py
dreamcreator/sequences/core/smu_sweep.py
dreamcreator/sequences/template/__init__.py
DreamCreator-0.0.25.dist-info/LICENSE
DreamCreator-0.0.25.dist-info/METADATA
DreamCreator-0.0.25.dist-info/WHEEL
DreamCreator-0.0.25.dist-info/top_level.txt
DreamCreator-0.0.25.dist-info/RECORD
