Metadata-Version: 2.1
Name: DreamCreator
Version: 0.0.25
Summary: A tool for creating YAML files for use in Dream Photonics and edx course
Home-page: https://github.com/dreamphotonics/DreamCreator.git
Author: Jonathan Barnes
Author-email: jonathanyorkbarnes@gmail.com
License: MIT
Classifier: Programming Language :: Python :: 3.10
Classifier: License :: OSI Approved :: MIT License
Classifier: Operating System :: OS Independent
Requires-Python: >=3.10
License-File: LICENSE
Requires-Dist: numpy >=1.26.3
Requires-Dist: pandas >=2.2.0
Requires-Dist: pillow >=10.2.0
Requires-Dist: pkginfo ==1.10.0
Requires-Dist: PyQt5 >=5.15.10
Requires-Dist: PyQt5-Qt5 >=5.15.2
Requires-Dist: PyQt5-sip >=12.13.0
Requires-Dist: pywin32-ctypes >=0.2.2
Requires-Dist: PyYAML >=6.0.1
Requires-Dist: scipy >=1.12.0
Requires-Dist: twine >=5.0.0
Requires-Dist: watchdog >=3.0.0
Requires-Dist: matplotlib >=3.8.2
